Workbook

Sheet Cover
C11: Practice Exercise - Lagos Trading - Blank | L11: Strictly Confidential
C13: Table of Contents
C15: Lagos Balance Sheet
C31: © 2015 to 2024 CFI Education Inc.
C32: This Excel model is for educational purposes only and should not be used for any other reason. All content is Copyright material of CFI Education Inc.
C33: All rights reserved. The contents of this publication, including but not limited to all written material, content layout, images, formulas, and code, are protected
C34: under international copyright and trademark laws. No part of this publication may be modified, manipulated, reproduced, distributed, or transmitted in any
C35: form by any means, including photocopying, recording, or other electronic or mechanical methods, without prior written permission of the publisher,
C36: except in the case of certain noncommercial uses permitted by copyright law.
C38: https://corporatefinanceinstitute.com/

Sheet Model
B3: Construct a Balance Sheet for Lagos Trading Inc.
B5: You have been asked to build a Balance Sheet for a company called Lagos Trading Inc. that has undertaken the following transactions
B7: 1. Issued common shares of 400.
B8: 2. Borrowed 200 from the bank for 5 years.
B9: 3. Bought property & equipment for 350 using cash.
B10: 4. Bought inventory of 150 on credit. The entire amount is still outstanding at the balance sheet date.
B11: 5. Sold 50% of the inventory for 200. 50 of this had been received in cash at the balance sheet date.
B12: 6. Paid a cash operating expense of 20.
B13: 7. Paid the bank interest of 10 for the loan.
B16: Balance Sheet
B18: ASSETS | G18: TOTAL LIABILITIES AND SHAREHOLDERS' EQUITY
B20: Current Assets | G20: Current Liabilities
B21: Cash | E21: 270 | F21: ='Model-R'!R21 | G21: Accounts Payable | K21: 150 | L21: ='Model-R'!V21
B22: Accounts Receivable | E22: 150 | F22: ='Model-R'!R22 | G22: Total Current Liabilties | K22: =SUM(K21)
B23: Inventory | E23: 75 | F23: ='Model-R'!R23
B24: Total Current Assets | E24: =SUM(E21:E23) | G24: Non-Current Liabilities
G25: Long-Term Debt | K25: 200 | L25: ='Model-R'!V25
B26: Non-Current Assets | G26: Total Non-Current Liabilities | K26: =SUM(K25)
B27: Property, Plant & Equipment | E27: 350 | F27: ='Model-R'!R27
B28: Total Non-Current Assets | E28: =SUM(E27) | G28: Shareholders' Equity
G29: Common Shares | K29: 400 | L29: ='Model-R'!V29
G30: Retained Earnings
G31: Revenue | K31: 200 | L31: ='Model-R'!V31
G32: Cost of Sales | K32: -75 | L32: ='Model-R'!V32
G33: Other Operating Expenses | K33: -20 | L33: ='Model-R'!V33
G34: Interest Expense | K34: -10 | L34: ='Model-R'!V34
H35: Total Retained Earnings | K35: =SUM(K31:K34)
G36: Total Shareholders' Equity | K36: =+K29+K35
B38: Total Assets | E38: =+E24+E28 | G38: Total Liabilities & Equity | K38: =+K36+K26+K22
C40: Total Assets | E40: =+E38 | K40: ='Model-R'!V36
C41: Total Liabilities & Equity | E41: =+K38
C42: Difference | E42: =+E40-E41
K44: For a value of zero, please enter a zero instead of leaving the cell blank.

Sheet Model-R
B3: Construct a Balance Sheet for Lagos Trading Inc.
B5: You have been asked to build a Balance Sheet for a company called Lagos Trading Inc. that has undertaken the following transactions
B7: 1. Issued common shares of 400.
B8: 2. Borrowed 200 from the bank for 5 years.
B9: 3. Bought property & equipment for 350 using cash.
B10: 4. Bought inventory of 150 on credit. The entire amount is still outstanding at the balance sheet date.
B11: 5. Sold 50% of the inventory for 200. 50 of this had been received in cash at the balance sheet date.
B12: 6. Paid a cash operating expense of 20.
B13: 7. Paid the bank interest of 10 for the loan.
B16: Balance Sheet
B18: ASSETS | G18: TOTAL LIABILITIES AND SHAREHOLDERS' EQUITY
B20: Current Assets | G20: Current Liabilities | P20: Learner | Q20: Correct | R20: Compare | T20: Learner | U20: Correct | V20: Compare
B21: Cash | E21: =400+200-350+50-20-10 | G21: Accounts Payable | K21: 150 | P21: =Model!E21 | Q21: =E21 | R21: =IFERROR(IF(P21=Q21,1,0),0) | T21: =Model!K21 | U21: =K21 | V21: =IFERROR(IF(T21=U21,1,0),0)
B22: Accounts Receivable | E22: 150 | G22: Total Current Liabilties | K22: =SUM(K21) | P22: =Model!E22 | Q22: =E22 | R22: =IFERROR(IF(P22=Q22,1,0),0)
B23: Inventory | E23: =150-75 | P23: =Model!E23 | Q23: =E23 | R23: =IFERROR(IF(P23=Q23,1,0),0)
B24: Total Current Assets | E24: =SUM(E21:E23) | G24: Non-Current Liabilities | T24: Learner | U24: Correct | V24: Compare
G25: Long-Term Debt | K25: 200 | T25: =Model!K25 | U25: =K25 | V25: =IFERROR(IF(T25=U25,1,0),0)
B26: Non-Current Assets | G26: Total Non-Current Liabilities | K26: =SUM(K25) | P26: Learner | Q26: Correct | R26: Compare
B27: Property, Plant & Equipment | E27: 350 | P27: =Model!E27 | Q27: =E27 | R27: =IFERROR(IF(P27=Q27,1,0),0)
B28: Total Non-Current Assets | E28: =SUM(E27) | G28: Shareholders' Equity | T28: Learner | U28: Correct | V28: Compare
G29: Common Shares | K29: 400 | T29: =Model!K29 | U29: =K29 | V29: =IFERROR(IF(T29=U29,1,0),0)
G30: Retained Earnings
G31: Revenue | K31: 200 | T31: =Model!K31 | U31: =K31 | V31: =IFERROR(IF(T31=U31,1,0),0)
G32: Cost of Sales | K32: -75 | T32: =Model!K32 | U32: =K32 | V32: =IFERROR(IF(T32=U32,1,0),0)
G33: Other Operating Expenses | K33: -20 | T33: =Model!K33 | U33: =K33 | V33: =IFERROR(IF(T33=U33,1,0),0)
G34: Interest Expense | K34: -10 | T34: =Model!K34 | U34: =K34 | V34: =IFERROR(IF(T34=U34,1,0),0)
H35: Total Retained Earnings | K35: =SUM(K31:K34)
G36: Total Shareholders' Equity | K36: =+K29+K35 | V36: =IF(SUM(V20:V34)+SUM(R20:R27)=11,"COMPLETE","")
B38: Total Assets | E38: =+E24+E28 | G38: Total Liabilities & Equity | K38: =+K36+K26+K22
C40: Total Assets | E40: =+E38
C41: Total Liabilities & Equity | E41: =+K38
C42: Difference | E42: =+E40-E41
